{
  "publicPath": "/assets/",
  "all": [
    "pages/catalog/index.fda982a2dc55515a22a2.js",
    "fonts/element-icons.2fad952.woff",
    "img/plumber.8b480e5.png",
    "img/phone_blue.43e9675.svg",
    "img/tools.20654c6.png",
    "img/avatar.8c0c7d3.svg",
    "img/gmail.09aea0f.svg",
    "img/sergey.ee77a01.png",
    "img/no_photo.3973539.svg",
    "img/tap.f57e88a.svg",
    "img/phone.12d2388.svg",
    "img/fingerprint.7ac60a3.svg",
    "img/two_speech.8add7db.svg",
    "img/pattern.235caf5.png",
    "img/services.2c7925e.png",
    "img/location.854e80f.svg",
    "img/rehigh_string_white.9a8ad18.svg",
    "img/emailSignIn.f1269b0.svg",
    "img/mozaika_1.9e52693.png",
    "img/product.16c2c1c.png",
    "img/mozaika_2.5d74676.png",
    "img/user-placeholder.0db7104.svg",
    "img/search_by_algolia.786d358.svg",
    "img/man.4deb46a.png",
    "img/calendar.6240f6f.svg",
    "img/search.2e4a635.svg",
    "img/shopping-cart.90d0051.svg",
    "pages/admin/system/index.c3785d9cd09639eb0cd8.js",
    "layouts/default.1b7253e4d64fcd971fe2.js",
    "pages/index.e5c951c231ddc9578b70.js",
    "pages/catalog/_group/index.eca3fc1a0f02df35ac6d.js",
    "pages/admin/products/index.26710213f7749e664dac.js",
    "pages/catalog/_group/_category/index.1392d9afe1a722dc7427.js",
    "pages/admin/requests/index.f0b9ac54c236173d1e21.js",
    "pages/cart/index.4d4ecbfb63089cc70526.js",
    "layouts/admin.c88db631c41543cc352b.js",
    "pages/admin/reviews/index.35705b2422863a352f0b.js",
    "pages/admin/orders/index.70f37fe55b18e9171322.js",
    "pages/admin/company/index.175bea326fa44312287e.js",
    "pages/about/index.e1954c1d42cea7672507.js",
    "pages/account/index.431a1fdbe3605871ec5c.js",
    "pages/admin/questions/index.7234dc7987c604eaf5f3.js",
    "pages/catalog/_group/_category/_id.210143f31b22cde5b8e2.js",
    "pages/admin/users/index.4d6f1627a084ec762507.js",
    "pages/admin/dictionaries/index.cc527b6c6b2e7caaae5b.js",
    "pages/login.1de988adedc1f2d86ac0.js",
    "fonts/element-icons.6f0a763.ttf",
    "pages/account/signin.2391de02e41dfe55f1cb.js",
    "pages/admin/index.3c47b6917f9016f3128b.js",
    "pages/account/signup.5aaf9aff23b7b63e666b.js",
    "common.5cbea586e56c406c641f.js",
    "app.b61a34abe1ede8624e59.js",
    "manifest.1bf6ee0308ea57baf359.js",
    "common.6931482d5f80f9cfc20128a36dac79dc.css",
    "LICENSES",
    "pages/admin/system/index.c3785d9cd09639eb0cd8.js.map",
    "layouts/default.1b7253e4d64fcd971fe2.js.map",
    "pages/index.e5c951c231ddc9578b70.js.map",
    "pages/catalog/_group/index.eca3fc1a0f02df35ac6d.js.map",
    "pages/admin/products/index.26710213f7749e664dac.js.map",
    "pages/catalog/_group/_category/index.1392d9afe1a722dc7427.js.map",
    "pages/admin/requests/index.f0b9ac54c236173d1e21.js.map",
    "pages/cart/index.4d4ecbfb63089cc70526.js.map",
    "layouts/admin.c88db631c41543cc352b.js.map",
    "pages/admin/reviews/index.35705b2422863a352f0b.js.map",
    "pages/admin/orders/index.70f37fe55b18e9171322.js.map",
    "pages/admin/company/index.175bea326fa44312287e.js.map",
    "pages/about/index.e1954c1d42cea7672507.js.map",
    "pages/account/index.431a1fdbe3605871ec5c.js.map",
    "pages/admin/questions/index.7234dc7987c604eaf5f3.js.map",
    "pages/catalog/_group/_category/_id.210143f31b22cde5b8e2.js.map",
    "pages/admin/users/index.4d6f1627a084ec762507.js.map",
    "pages/admin/dictionaries/index.cc527b6c6b2e7caaae5b.js.map",
    "pages/login.1de988adedc1f2d86ac0.js.map",
    "pages/catalog/index.fda982a2dc55515a22a2.js.map",
    "pages/account/signin.2391de02e41dfe55f1cb.js.map",
    "pages/admin/index.3c47b6917f9016f3128b.js.map",
    "pages/account/signup.5aaf9aff23b7b63e666b.js.map",
    "common.5cbea586e56c406c641f.js.map",
    "app.b61a34abe1ede8624e59.js.map",
    "common.6931482d5f80f9cfc20128a36dac79dc.css.map",
    "manifest.1bf6ee0308ea57baf359.js.map",
    "icons/icon_64.8HD18iheCtI.png",
    "icons/icon_120.8HD18iheCtI.png",
    "icons/icon_144.8HD18iheCtI.png",
    "icons/icon_152.8HD18iheCtI.png",
    "icons/icon_192.8HD18iheCtI.png",
    "icons/icon_384.8HD18iheCtI.png",
    "icons/icon_512.8HD18iheCtI.png",
    "manifest.7bee7afc.json",
    "index.spa.html",
    "index.ssr.html"
  ],
  "initial": [
    "manifest.1bf6ee0308ea57baf359.js",
    "common.5cbea586e56c406c641f.js",
    "app.b61a34abe1ede8624e59.js"
  ],
  "async": [
    "pages/catalog/index.fda982a2dc55515a22a2.js",
    "pages/admin/system/index.c3785d9cd09639eb0cd8.js",
    "layouts/default.1b7253e4d64fcd971fe2.js",
    "pages/index.e5c951c231ddc9578b70.js",
    "pages/catalog/_group/index.eca3fc1a0f02df35ac6d.js",
    "pages/admin/products/index.26710213f7749e664dac.js",
    "pages/catalog/_group/_category/index.1392d9afe1a722dc7427.js",
    "pages/admin/requests/index.f0b9ac54c236173d1e21.js",
    "pages/cart/index.4d4ecbfb63089cc70526.js",
    "layouts/admin.c88db631c41543cc352b.js",
    "pages/admin/reviews/index.35705b2422863a352f0b.js",
    "pages/admin/orders/index.70f37fe55b18e9171322.js",
    "pages/admin/company/index.175bea326fa44312287e.js",
    "pages/about/index.e1954c1d42cea7672507.js",
    "pages/account/index.431a1fdbe3605871ec5c.js",
    "pages/admin/questions/index.7234dc7987c604eaf5f3.js",
    "pages/catalog/_group/_category/_id.210143f31b22cde5b8e2.js",
    "pages/admin/users/index.4d6f1627a084ec762507.js",
    "pages/admin/dictionaries/index.cc527b6c6b2e7caaae5b.js",
    "pages/login.1de988adedc1f2d86ac0.js",
    "pages/account/signin.2391de02e41dfe55f1cb.js",
    "pages/admin/index.3c47b6917f9016f3128b.js",
    "pages/account/signup.5aaf9aff23b7b63e666b.js"
  ],
  "modules": {
    "13224647": [
      27,
      55
    ],
    "13439159": [
      36,
      64
    ],
    "13992033": [
      51,
      53,
      79,
      80
    ],
    "18054950": [
      50,
      78
    ],
    "23251991": [
      50,
      78
    ],
    "27608386": [
      29,
      57,
      3,
      4,
      5,
      7,
      12,
      14,
      18,
      19,
      20,
      23
    ],
    "42810480": [
      51,
      53,
      79,
      80
    ],
    "49798874": [
      0,
      74,
      9,
      21
    ],
    "54170002": [
      50,
      78
    ],
    "58757086": [
      27,
      55
    ],
    "63820290": [
      36,
      64
    ],
    "67887383": [
      38,
      66
    ],
    "69617997": [
      29,
      57,
      3,
      4,
      5,
      7,
      12,
      14,
      18,
      19,
      20,
      23
    ],
    "69649463": [
      51,
      53,
      79,
      80
    ],
    "69698162": [
      50,
      78
    ],
    "71439757": [
      50,
      78
    ],
    "71519153": [
      50,
      78
    ],
    "72015786": [
      27,
      55
    ],
    "80846240": [
      29,
      57,
      3,
      4,
      5,
      7,
      12,
      14,
      18,
      19,
      20,
      23
    ],
    "40f99bf4": [
      50,
      78
    ],
    "1204c383": [
      37,
      65
    ],
    "8bdd54c0": [
      35,
      63
    ],
    "738114e4": [
      50,
      78
    ],
    "4090c5a0": [
      39,
      67,
      2,
      13
    ],
    "5c89cca1": [
      27,
      55
    ],
    "56cd48b5": [
      51,
      53,
      79,
      80
    ],
    "121fcb86": [
      33,
      61
    ],
    "055023c1": [
      50,
      78
    ],
    "44bed32e": [
      35,
      63
    ],
    "c6298e08": [
      51,
      53,
      79,
      80
    ],
    "1d8a6c6b": [
      29,
      57,
      3,
      4,
      5,
      7,
      12,
      14,
      18,
      19,
      20,
      23
    ],
    "c334279e": [
      50,
      78
    ],
    "757b625c": [
      27,
      55
    ],
    "369b5da4": [
      27,
      55
    ],
    "a62133f0": [
      50,
      78
    ],
    "1f70bdc1": [
      31,
      59
    ],
    "aff6fb46": [
      27,
      55
    ],
    "48ce8985": [
      50,
      78
    ],
    "465134bc": [
      50,
      78
    ],
    "7ea6a762": [
      49,
      77
    ],
    "20c3d8e2": [
      27,
      55
    ],
    "25efd366": [
      29,
      57,
      3,
      4,
      5,
      7,
      12,
      14,
      18,
      19,
      20,
      23
    ],
    "ba77df94": [
      37,
      65
    ],
    "347cdaba": [
      50,
      78
    ],
    "1f8c569a": [
      50,
      78
    ],
    "4584e812": [
      50,
      78
    ],
    "eb1e0790": [
      34,
      62
    ],
    "1cd46206": [
      35,
      63
    ],
    "6f68bdfe": [
      50,
      78
    ],
    "c8103abe": [
      50,
      78
    ],
    "d1e8d43c": [
      27,
      55
    ],
    "5dafb35c": [
      28,
      56,
      3,
      5,
      8,
      10,
      12,
      15,
      16,
      22,
      24,
      25,
      26
    ],
    "3be454e3": [
      41,
      69
    ],
    "c06a237c": [
      33,
      61
    ],
    "1ca9fb2e": [
      51,
      53,
      79,
      80
    ],
    "6fa3ec28": [
      50,
      78
    ],
    "4d186eb9": [
      49,
      77
    ],
    "ae946dcc": [
      47,
      75,
      6,
      17
    ],
    "8566c9c2": [
      45,
      73
    ],
    "6f568659": [
      51,
      53,
      79,
      80
    ],
    "5acdb340": [
      30,
      58
    ],
    "eeaf1586": [
      42,
      70
    ],
    "39da4048": [
      39,
      67,
      2,
      13
    ],
    "f7adaa40": [
      43,
      71
    ],
    "b88ce204": [
      27,
      55
    ],
    "072ebae6": [
      29,
      57,
      3,
      4,
      5,
      7,
      12,
      14,
      18,
      19,
      20,
      23
    ],
    "6ff174ef": [
      50,
      78
    ],
    "61154d42": [
      50,
      78
    ],
    "7248b03e": [
      29,
      57,
      3,
      4,
      5,
      7,
      12,
      14,
      18,
      19,
      20,
      23
    ],
    "5e8a4665": [
      33,
      61
    ],
    "4a955cfb": [
      43,
      71
    ],
    "3cdcb35e": [
      27,
      55
    ],
    "6609cf40": [
      50,
      78
    ],
    "3cb233f3": [
      50,
      78
    ],
    "78944d56": [
      0,
      74,
      9,
      21
    ],
    "b3fa0094": [
      34,
      62
    ],
    "7dc7a67e": [
      27,
      55
    ],
    "603fc96a": [
      41,
      69
    ],
    "2e4c1cd7": [
      0,
      74,
      9,
      21
    ],
    "69aacc8d": [
      50,
      78
    ],
    "34e32a67": [
      45,
      73
    ],
    "47ccdd66": [
      48,
      76
    ],
    "8567c0e0": [
      49,
      77
    ],
    "500c43fe": [
      33,
      61
    ],
    "236344f8": [
      50,
      78
    ],
    "1617dee2": [
      50,
      78
    ],
    "639918d0": [
      50,
      78
    ],
    "56b1f9fa": [
      51,
      53,
      79,
      80
    ],
    "0a8c0f9a": [
      27,
      55
    ],
    "19848d4f": [
      51,
      53,
      79,
      80
    ],
    "37a8a5b3": [
      50,
      78
    ],
    "125f65e2": [
      50,
      78
    ],
    "35ad021b": [
      51,
      53,
      79,
      80
    ],
    "22a6d5b7": [
      27,
      55
    ],
    "7495275e": [
      50,
      78
    ],
    "09b870a2": [
      51,
      53,
      79,
      80
    ],
    "174d5888": [
      47,
      75,
      6,
      17
    ],
    "04d34c16": [
      51,
      53,
      79,
      80
    ],
    "7616563a": [
      35,
      63
    ],
    "d021c186": [
      50,
      78
    ],
    "6a09b44a": [
      51,
      53,
      79,
      80
    ],
    "5e903d33": [
      51,
      53,
      79,
      80
    ],
    "5a3283bf": [
      34,
      62
    ],
    "02e4141f": [
      50,
      78
    ],
    "836768f0": [
      32,
      60
    ],
    "6cfc1cd8": [
      50,
      78
    ],
    "7ea5b044": [
      45,
      73
    ],
    "4586ddbe": [
      40,
      68,
      11,
      21
    ],
    "cdb1265a": [
      50,
      78
    ],
    "46a0792a": [
      51,
      53,
      79,
      80
    ],
    "dadb0a56": [
      30,
      58
    ],
    "685753b3": [
      30,
      58
    ],
    "50a89cfa": [
      31,
      59
    ],
    "7d843aea": [
      27,
      55
    ],
    "23abe3c0": [
      41,
      69
    ],
    "35df1770": [
      31,
      59
    ],
    "5776a400": [
      29,
      57,
      3,
      4,
      5,
      7,
      12,
      14,
      18,
      19,
      20,
      23
    ],
    "631c9169": [
      28,
      56,
      3,
      5,
      8,
      10,
      12,
      15,
      16,
      22,
      24,
      25,
      26
    ],
    "5c012525": [
      35,
      63
    ],
    "e37c3cb4": [
      51,
      53,
      79,
      80
    ],
    "5bdb85dd": [
      27,
      55
    ],
    "389bf11d": [
      50,
      78
    ],
    "231551c1": [
      27,
      55
    ],
    "2c5a2a7d": [
      31,
      59
    ],
    "42f9a549": [
      50,
      78
    ],
    "ae11ce00": [
      50,
      78
    ],
    "51c89efa": [
      50,
      78
    ],
    "4592db90": [
      50,
      78
    ],
    "6b104176": [
      42,
      70
    ],
    "549a4a1b": [
      50,
      78
    ],
    "be60e3fe": [
      27,
      55
    ],
    "6b6406de": [
      45,
      73
    ],
    "6f4ba5aa": [
      29,
      57,
      3,
      4,
      5,
      7,
      12,
      14,
      18,
      19,
      20,
      23
    ],
    "0e3d7e82": [
      45,
      73
    ],
    "4c98a79f": [
      50,
      78
    ],
    "4b9089f0": [
      27,
      55
    ],
    "165936d8": [
      50,
      78
    ],
    "430931ab": [
      51,
      53,
      79,
      80
    ],
    "fbc8ad36": [
      30,
      58
    ],
    "eb3cc9c4": [
      31,
      59
    ],
    "14a70bc8": [
      33,
      61
    ],
    "646641c6": [
      34,
      62
    ],
    "0ce42456": [
      40,
      68,
      11,
      21
    ],
    "2730e306": [
      0,
      74,
      9,
      21
    ],
    "561735b5": [
      51,
      53,
      79,
      80
    ],
    "bb3df2d8": [
      35,
      63
    ],
    "5678ba28": [
      51,
      53,
      79,
      80
    ],
    "2c2b8966": [
      27,
      55
    ],
    "6f7c16b2": [
      27,
      55
    ],
    "2684e3bc": [
      34,
      62
    ],
    "0b76ad52": [
      37,
      65
    ],
    "96cb321e": [
      34,
      62
    ],
    "1f18dfe9": [
      30,
      58
    ],
    "a8f7edac": [
      39,
      67,
      2,
      13
    ],
    "ed11ee82": [
      50,
      78
    ],
    "b6169bbc": [
      33,
      61
    ],
    "677b2dfa": [
      45,
      73
    ],
    "1e8a4f32": [
      50,
      78
    ],
    "0c14a855": [
      34,
      62
    ],
    "3062905a": [
      27,
      55
    ],
    "07514525": [
      51,
      53,
      79,
      80
    ],
    "0ca9ad8c": [
      47,
      75,
      6,
      17
    ],
    "99eee340": [
      33,
      61
    ],
    "6626dada": [
      29,
      57,
      3,
      4,
      5,
      7,
      12,
      14,
      18,
      19,
      20,
      23
    ],
    "660d651c": [
      36,
      64
    ],
    "cabd305e": [
      51,
      53,
      79,
      80
    ],
    "6dcf7b92": [
      31,
      59
    ],
    "00cc6974": [
      50,
      78
    ],
    "665ea1d6": [
      27,
      55
    ],
    "9162e2ec": [
      38,
      66
    ],
    "13093ce5": [
      43,
      71
    ],
    "1bb1838a": [
      50,
      78
    ],
    "e5fe9998": [
      50,
      78
    ],
    "0d94b891": [
      27,
      55
    ],
    "dbadca66": [
      28,
      56,
      3,
      5,
      8,
      10,
      12,
      15,
      16,
      22,
      24,
      25,
      26
    ],
    "21a33868": [
      44,
      72
    ],
    "32b333c4": [
      28,
      56,
      3,
      5,
      8,
      10,
      12,
      15,
      16,
      22,
      24,
      25,
      26
    ],
    "041beef0": [
      50,
      78
    ],
    "5e61eabb": [
      27,
      55
    ],
    "2a0789c8": [
      50,
      78
    ],
    "f27ab77e": [
      51,
      53,
      79,
      80
    ],
    "f2d4fb5a": [
      35,
      63
    ],
    "e2793456": [
      51,
      53,
      79,
      80
    ],
    "1520fb36": [
      41,
      69
    ],
    "6d86b0a1": [
      27,
      55
    ],
    "0cca5a6e": [
      50,
      78
    ],
    "233b51f2": [
      50,
      78
    ],
    "16e0b45f": [
      50,
      78
    ],
    "fb9599fa": [
      50,
      78
    ],
    "4ef98eed": [
      37,
      65
    ],
    "2f26ccbc": [
      50,
      78
    ],
    "338efe94": [
      50,
      78
    ],
    "4d76551d": [
      28,
      56,
      3,
      5,
      8,
      10,
      12,
      15,
      16,
      22,
      24,
      25,
      26
    ],
    "492ed12c": [
      34,
      62
    ],
    "051de861": [
      27,
      55
    ],
    "194cdabc": [
      50,
      78
    ],
    "67c4d6af": [
      51,
      53,
      79,
      80
    ],
    "331b010e": [
      29,
      57,
      3,
      4,
      5,
      7,
      12,
      14,
      18,
      19,
      20,
      23
    ],
    "6cde495a": [
      50,
      78
    ],
    "c4a173cc": [
      44,
      72
    ],
    "7a760651": [
      35,
      63
    ],
    "c22432f2": [
      50,
      78
    ],
    "8ca0daca": [
      51,
      53,
      79,
      80
    ],
    "3fe96474": [
      35,
      63
    ],
    "b1e0c7cc": [
      50,
      78
    ],
    "00aac8c7": [
      51,
      53,
      79,
      80
    ],
    "28619de2": [
      42,
      70
    ],
    "029ac5ec": [
      29,
      57,
      3,
      4,
      5,
      7,
      12,
      14,
      18,
      19,
      20,
      23
    ],
    "24ea299e": [
      34,
      62
    ],
    "1e1e8d14": [
      51,
      53,
      79,
      80
    ],
    "1159860c": [
      51,
      53,
      79,
      80
    ],
    "4b31676b": [
      27,
      55
    ],
    "2a68ee37": [
      29,
      57,
      3,
      4,
      5,
      7,
      12,
      14,
      18,
      19,
      20,
      23
    ],
    "7b6b79cd": [
      44,
      72
    ],
    "41b342ec": [
      40,
      68,
      11,
      21
    ],
    "10b87e9a": [
      50,
      78
    ],
    "68fe4e06": [
      50,
      78
    ],
    "4a2f0f0a": [
      29,
      57,
      3,
      4,
      5,
      7,
      12,
      14,
      18,
      19,
      20,
      23
    ],
    "b8b41e8c": [
      51,
      53,
      79,
      80
    ],
    "f17bd3f2": [
      33,
      61
    ],
    "a087899c": [
      32,
      60
    ],
    "97365c84": [
      50,
      78
    ],
    "7fc9d55a": [
      28,
      56,
      3,
      5,
      8,
      10,
      12,
      15,
      16,
      22,
      24,
      25,
      26
    ],
    "bf5228c6": [
      27,
      55
    ],
    "1d0cf778": [
      28,
      56,
      3,
      5,
      8,
      10,
      12,
      15,
      16,
      22,
      24,
      25,
      26
    ],
    "091bd880": [
      40,
      68,
      11,
      21
    ],
    "d448aecc": [
      51,
      53,
      79,
      80
    ],
    "c820aa72": [
      50,
      78
    ],
    "a0d11d3e": [
      29,
      57,
      3,
      4,
      5,
      7,
      12,
      14,
      18,
      19,
      20,
      23
    ],
    "e86291aa": [
      48,
      76
    ],
    "77aa61f0": [
      51,
      53,
      79,
      80
    ],
    "505f63d6": [
      27,
      55
    ],
    "64b46d82": [
      29,
      57,
      3,
      4,
      5,
      7,
      12,
      14,
      18,
      19,
      20,
      23
    ],
    "c2f6442c": [
      41,
      69
    ],
    "211d8b5c": [
      49,
      77
    ],
    "e0bd1b6e": [
      31,
      59
    ],
    "b9473520": [
      50,
      78
    ],
    "6cb6808f": [
      27,
      55
    ],
    "0afb3acf": [
      31,
      59
    ],
    "6692e002": [
      27,
      55
    ],
    "c099318c": [
      36,
      64
    ],
    "1e92a1ce": [
      35,
      63
    ],
    "60d66ca2": [
      51,
      53,
      79,
      80
    ],
    "1b93606e": [
      50,
      78
    ],
    "2e3e59c2": [
      39,
      67,
      2,
      13
    ],
    "fca90b76": [
      28,
      56,
      3,
      5,
      8,
      10,
      12,
      15,
      16,
      22,
      24,
      25,
      26
    ],
    "9dd729a6": [
      35,
      63
    ],
    "35c67a32": [
      50,
      78
    ],
    "00643108": [
      27,
      55
    ],
    "07f218fe": [
      51,
      53,
      79,
      80
    ],
    "43ef1bb2": [
      28,
      56,
      3,
      5,
      8,
      10,
      12,
      15,
      16,
      22,
      24,
      25,
      26
    ],
    "38d128d8": [
      31,
      59
    ],
    "5f928ecd": [
      41,
      69
    ],
    "0a4fba0c": [
      27,
      55
    ],
    "4faa8d90": [
      29,
      57,
      3,
      4,
      5,
      7,
      12,
      14,
      18,
      19,
      20,
      23
    ],
    "7fd304d3": [
      40,
      68,
      11,
      21
    ],
    "1850c132": [
      34,
      62
    ],
    "7c51493b": [
      29,
      57,
      3,
      4,
      5,
      7,
      12,
      14,
      18,
      19,
      20,
      23
    ],
    "fcf607e2": [
      31,
      59
    ],
    "4868b4bc": [
      50,
      78
    ],
    "0e1870f2": [
      50,
      78
    ],
    "64b32920": [
      28,
      56,
      3,
      5,
      8,
      10,
      12,
      15,
      16,
      22,
      24,
      25,
      26
    ],
    "541ab35e": [
      50,
      78
    ],
    "6e5d6a6a": [
      0,
      74,
      9,
      21
    ],
    "72e603a5": [
      42,
      70
    ],
    "b0fc2ca8": [
      30,
      58
    ],
    "77dce3a8": [
      28,
      56,
      3,
      5,
      8,
      10,
      12,
      15,
      16,
      22,
      24,
      25,
      26
    ],
    "2391af22": [
      32,
      60
    ],
    "37f92aa1": [
      41,
      69
    ],
    "54bb2e0b": [
      27,
      55
    ],
    "8c94a62c": [
      41,
      69
    ],
    "f0c107e6": [
      33,
      61
    ],
    "f648c56e": [
      27,
      55
    ],
    "ae4f8554": [
      51,
      53,
      79,
      80
    ],
    "4fbb79b9": [
      28,
      56,
      3,
      5,
      8,
      10,
      12,
      15,
      16,
      22,
      24,
      25,
      26
    ],
    "3bcb373e": [
      51,
      53,
      79,
      80
    ],
    "25b18ad2": [
      45,
      73
    ],
    "55dff4a4": [
      51,
      53,
      79,
      80
    ],
    "7022de75": [
      50,
      78
    ],
    "69bf425b": [
      27,
      55
    ],
    "e1293808": [
      27,
      55
    ],
    "07669321": [
      50,
      78
    ],
    "b113bcf4": [
      51,
      53,
      79,
      80
    ],
    "75ed5000": [
      40,
      68,
      11,
      21
    ],
    "7e51a48e": [
      51,
      53,
      79,
      80
    ],
    "e98044cc": [
      51,
      53,
      79,
      80
    ],
    "4d7f137a": [
      27,
      55
    ],
    "e9144062": [
      27,
      55
    ],
    "6feaa35e": [
      50,
      78
    ],
    "5db42486": [
      27,
      55
    ],
    "a7d3544e": [
      47,
      75,
      6,
      17
    ],
    "5241c760": [
      28,
      56,
      3,
      5,
      8,
      10,
      12,
      15,
      16,
      22,
      24,
      25,
      26
    ],
    "983e4f62": [
      50,
      78
    ],
    "58e8edc8": [
      34,
      62
    ],
    "85e8761e": [
      0,
      74,
      9,
      21
    ],
    "00d5bf34": [
      50,
      78
    ],
    "1c2ff364": [
      28,
      56,
      3,
      5,
      8,
      10,
      12,
      15,
      16,
      22,
      24,
      25,
      26
    ],
    "18f0a0e0": [
      50,
      78
    ],
    "116cdf55": [
      51,
      53,
      79,
      80
    ],
    "4a0ada0e": [
      27,
      55
    ],
    "a925718a": [
      38,
      66
    ],
    "aa44017e": [
      28,
      56,
      3,
      5,
      8,
      10,
      12,
      15,
      16,
      22,
      24,
      25,
      26
    ],
    "2583a544": [
      51,
      53,
      79,
      80
    ],
    "7b692119": [
      50,
      78
    ],
    "ce2ecec6": [
      32,
      60
    ],
    "5f1f5f91": [
      50,
      78
    ],
    "2a967aa6": [
      30,
      58
    ],
    "5b782271": [
      39,
      67,
      2,
      13
    ],
    "459e18aa": [
      35,
      63
    ],
    "c559499a": [
      50,
      78
    ],
    "29fba4e8": [
      38,
      66
    ],
    "705cae7f": [
      30,
      58
    ],
    "00b6e902": [
      36,
      64
    ],
    "8101a06a": [
      50,
      78
    ],
    "a16c79e4": [
      50,
      78
    ],
    "404cb17f": [
      28,
      56,
      3,
      5,
      8,
      10,
      12,
      15,
      16,
      22,
      24,
      25,
      26
    ],
    "c8bfca38": [
      37,
      65
    ],
    "3dddbe70": [
      50,
      78
    ],
    "34b1d4d0": [
      28,
      56,
      3,
      5,
      8,
      10,
      12,
      15,
      16,
      22,
      24,
      25,
      26
    ],
    "1167dfb1": [
      34,
      62
    ],
    "8ce98100": [
      40,
      68,
      11,
      21
    ],
    "d02ad274": [
      38,
      66
    ],
    "1d66782d": [
      50,
      78
    ],
    "23f1a5a0": [
      50,
      78
    ],
    "e0fa91b4": [
      34,
      62
    ],
    "755bcd06": [
      50,
      78
    ],
    "7040bd76": [
      0,
      74,
      9,
      21
    ],
    "04a0f382": [
      50,
      78
    ],
    "09760471": [
      50,
      78
    ],
    "f2352396": [
      50,
      78
    ],
    "35605ab0": [
      35,
      63
    ],
    "5a081c2e": [
      37,
      65
    ],
    "7eaed993": [
      34,
      62
    ],
    "5b74b900": [
      36,
      64
    ],
    "ff959770": [
      33,
      61
    ],
    "0bf60a1e": [
      29,
      57,
      3,
      4,
      5,
      7,
      12,
      14,
      18,
      19,
      20,
      23
    ],
    "2137e13a": [
      28,
      56,
      3,
      5,
      8,
      10,
      12,
      15,
      16,
      22,
      24,
      25,
      26
    ],
    "d3389208": [
      51,
      53,
      79,
      80
    ],
    "1cd9de6d": [
      28,
      56,
      3,
      5,
      8,
      10,
      12,
      15,
      16,
      22,
      24,
      25,
      26
    ],
    "666393aa": [
      37,
      65
    ],
    "9bcfc69a": [
      39,
      67,
      2,
      13
    ],
    "304bf2f0": [
      29,
      57,
      3,
      4,
      5,
      7,
      12,
      14,
      18,
      19,
      20,
      23
    ],
    "f02a2a68": [
      36,
      64
    ],
    "ac63f936": [
      32,
      60
    ],
    "f3a186ca": [
      33,
      61
    ],
    "4103e676": [
      50,
      78
    ],
    "5bc69924": [
      50,
      78
    ],
    "d53d91f2": [
      31,
      59
    ],
    "c164a33c": [
      35,
      63
    ],
    "df81e42a": [
      27,
      55
    ],
    "2b2affe2": [
      30,
      58
    ],
    "865edde0": [
      50,
      78
    ],
    "de307cde": [
      50,
      78
    ],
    "2ca6386a": [
      39,
      67,
      2,
      13
    ],
    "13a403c6": [
      43,
      71
    ],
    "2ef88c9e": [
      36,
      64
    ],
    "c5354f9c": [
      51,
      53,
      79,
      80
    ],
    "16e01828": [
      34,
      62
    ],
    "5d8d9ad0": [
      50,
      78
    ],
    "5e9e93ad": [
      50,
      78
    ],
    "05017f8e": [
      50,
      78
    ],
    "0ef6a4d9": [
      28,
      56,
      3,
      5,
      8,
      10,
      12,
      15,
      16,
      22,
      24,
      25,
      26
    ],
    "a698718a": [
      50,
      78
    ],
    "8ce1afc8": [
      50,
      78
    ],
    "2f282b19": [
      50,
      78
    ],
    "67db2a5a": [
      37,
      65
    ],
    "528203a9": [
      39,
      67,
      2,
      13
    ],
    "3ae6f940": [
      50,
      78
    ],
    "30670bb1": [
      27,
      55
    ],
    "263779d3": [
      50,
      78
    ],
    "119266f2": [
      43,
      71
    ],
    "329206d0": [
      27,
      55
    ],
    "38077d31": [
      28,
      56,
      3,
      5,
      8,
      10,
      12,
      15,
      16,
      22,
      24,
      25,
      26
    ],
    "581c889a": [
      47,
      75,
      6,
      17
    ],
    "a55551f2": [
      35,
      63
    ],
    "1f2bc4c6": [
      33,
      61
    ],
    "7265d8b0": [
      50,
      78
    ],
    "4718082f": [
      50,
      78
    ],
    "68d70395": [
      33,
      61
    ],
    "03c69a48": [
      41,
      69
    ],
    "6ef021fd": [
      51,
      53,
      79,
      80
    ],
    "d543a2fc": [
      42,
      70
    ],
    "521fafb6": [
      50,
      78
    ],
    "4e463016": [
      41,
      69
    ],
    "1c117bcf": [
      35,
      63
    ],
    "0e304224": [
      35,
      63
    ],
    "a4f3ae8e": [
      38,
      66
    ],
    "1e51b51a": [
      50,
      78
    ],
    "3233f2e5": [
      51,
      53,
      79,
      80
    ],
    "7175f430": [
      50,
      78
    ],
    "9e5b9384": [
      37,
      65
    ],
    "3a1846aa": [
      29,
      57,
      3,
      4,
      5,
      7,
      12,
      14,
      18,
      19,
      20,
      23
    ],
    "8ae1ef9a": [
      51,
      53,
      79,
      80
    ],
    "1fcf3caa": [
      50,
      78
    ],
    "054fb245": [
      51,
      53,
      79,
      80
    ],
    "a57a1cca": [
      31,
      59
    ],
    "75d80bdd": [
      50,
      78
    ],
    "2d4510db": [
      31,
      59
    ],
    "5f64c15c": [
      39,
      67,
      2,
      13
    ],
    "098ccac4": [
      27,
      55
    ],
    "6df1325e": [
      31,
      59
    ],
    "d4ecb0e8": [
      28,
      56,
      3,
      5,
      8,
      10,
      12,
      15,
      16,
      22,
      24,
      25,
      26
    ],
    "88f7101e": [
      29,
      57,
      3,
      4,
      5,
      7,
      12,
      14,
      18,
      19,
      20,
      23
    ],
    "aeb82198": [
      27,
      55
    ],
    "260c7c1a": [
      50,
      78
    ],
    "23f06b4d": [
      38,
      66
    ],
    "81b80466": [
      49,
      77
    ],
    "a178080e": [
      50,
      78
    ],
    "3f1c78de": [
      34,
      62
    ],
    "2b8d07f4": [
      27,
      55
    ],
    "340e1e45": [
      42,
      70
    ],
    "3e302c53": [
      50,
      78
    ],
    "ea51650c": [
      33,
      61
    ],
    "fc57bada": [
      50,
      78
    ],
    "02e5c594": [
      50,
      78
    ],
    "855cbbea": [
      50,
      78
    ],
    "60f3900e": [
      34,
      62
    ],
    "471a0cd6": [
      36,
      64
    ],
    "ce74182a": [
      39,
      67,
      2,
      13
    ],
    "1f3e2a03": [
      28,
      56,
      3,
      5,
      8,
      10,
      12,
      15,
      16,
      22,
      24,
      25,
      26
    ],
    "810700a4": [
      30,
      58
    ],
    "4807e9d1": [
      36,
      64
    ],
    "b3d859ca": [
      37,
      65
    ],
    "038d8c00": [
      27,
      55
    ],
    "1324d2ea": [
      50,
      78
    ],
    "651a6324": [
      27,
      55
    ],
    "1d7ac1df": [
      50,
      78
    ],
    "8cdc12b0": [
      51,
      53,
      79,
      80
    ],
    "6b974f60": [
      33,
      61
    ],
    "bb46a170": [
      50,
      78
    ],
    "681dab70": [
      50,
      78
    ],
    "f734b400": [
      50,
      78
    ],
    "25e69720": [
      50,
      78
    ],
    "78df6906": [
      37,
      65
    ],
    "9b9fe952": [
      28,
      56,
      3,
      5,
      8,
      10,
      12,
      15,
      16,
      22,
      24,
      25,
      26
    ],
    "135ba14c": [
      28,
      56,
      3,
      5,
      8,
      10,
      12,
      15,
      16,
      22,
      24,
      25,
      26
    ],
    "05dbaf7c": [
      27,
      55
    ],
    "8195ab04": [
      50,
      78
    ],
    "ba68c0ea": [
      29,
      57,
      3,
      4,
      5,
      7,
      12,
      14,
      18,
      19,
      20,
      23
    ],
    "08316bd3": [
      32,
      60
    ],
    "68449edd": [
      42,
      70
    ],
    "6506eb66": [
      50,
      78
    ],
    "02b19b2e": [
      51,
      53,
      79,
      80
    ],
    "6a0375dc": [
      27,
      55
    ],
    "11767f52": [
      29,
      57,
      3,
      4,
      5,
      7,
      12,
      14,
      18,
      19,
      20,
      23
    ],
    "087d6c46": [
      51,
      53,
      79,
      80
    ],
    "16d5d3de": [
      50,
      78
    ],
    "1454134a": [
      28,
      56,
      3,
      5,
      8,
      10,
      12,
      15,
      16,
      22,
      24,
      25,
      26
    ],
    "5d607c16": [
      31,
      59
    ],
    "2d97c38b": [
      28,
      56,
      3,
      5,
      8,
      10,
      12,
      15,
      16,
      22,
      24,
      25,
      26
    ],
    "43ccfa1a": [
      50,
      78
    ],
    "2a5844d2": [
      27,
      55
    ],
    "113d22f3": [
      51,
      53,
      79,
      80
    ],
    "38a844e4": [
      50,
      78
    ],
    "4bfae4e1": [
      29,
      57,
      3,
      4,
      5,
      7,
      12,
      14,
      18,
      19,
      20,
      23
    ],
    "39abcdac": [
      48,
      76
    ],
    "0373f2f2": [
      50,
      78
    ],
    "d10ed136": [
      37,
      65
    ],
    "dc98d178": [
      36,
      64
    ],
    "415521d3": [
      38,
      66
    ],
    "63c9cd16": [
      51,
      53,
      79,
      80
    ],
    "d293c1a2": [
      50,
      78
    ],
    "92a08d38": [
      45,
      73
    ],
    "4e5af448": [
      47,
      75,
      6,
      17
    ],
    "706670ee": [
      50,
      78
    ],
    "3b7a63bb": [
      31,
      59
    ],
    "4c312dd7": [
      50,
      78
    ],
    "3bf2953e": [
      36,
      64
    ],
    "b4985928": [
      51,
      53,
      79,
      80
    ],
    "1f247148": [
      32,
      60
    ],
    "beefc13c": [
      51,
      53,
      79,
      80
    ],
    "d6a7a39a": [
      51,
      53,
      79,
      80
    ],
    "465ea0f6": [
      27,
      55
    ],
    "cdd5558c": [
      51,
      53,
      79,
      80
    ],
    "28dc21a1": [
      51,
      53,
      79,
      80
    ],
    "70fcd338": [
      30,
      58
    ],
    "2cfbecdf": [
      51,
      53,
      79,
      80
    ],
    "a53150c0": [
      27,
      55
    ],
    "5b655986": [
      48,
      76
    ],
    "6cd2a50e": [
      27,
      55
    ],
    "34f0517a": [
      50,
      78
    ],
    "bfe79086": [
      50,
      78
    ],
    "1a32a382": [
      39,
      67,
      2,
      13
    ],
    "14054e1e": [
      29,
      57,
      3,
      4,
      5,
      7,
      12,
      14,
      18,
      19,
      20,
      23
    ],
    "6f68dc74": [
      31,
      59
    ],
    "23bf29a8": [
      27,
      55
    ],
    "8b6d86e4": [
      34,
      62
    ],
    "8ebe2872": [
      50,
      78
    ],
    "4190efb2": [
      35,
      63
    ],
    "26eff6c9": [
      50,
      78
    ],
    "42fe4760": [
      50,
      78
    ],
    "1085a031": [
      51,
      53,
      79,
      80
    ],
    "3d1ee289": [
      51,
      53,
      79,
      80
    ],
    "1fef82c4": [
      51,
      53,
      79,
      80
    ],
    "dbd96860": [
      50,
      78
    ],
    "8e34cea8": [
      34,
      62
    ],
    "05e9d960": [
      51,
      53,
      79,
      80
    ],
    "1af3747e": [
      50,
      78
    ],
    "12257a1e": [
      51,
      53,
      79,
      80
    ],
    "1b23a26a": [
      27,
      55
    ],
    "17f75723": [
      50,
      78
    ],
    "6668b49a": [
      38,
      66
    ],
    "61b73881": [
      50,
      78
    ],
    "65a8783c": [
      50,
      78
    ],
    "39fc17a8": [
      29,
      57,
      3,
      4,
      5,
      7,
      12,
      14,
      18,
      19,
      20,
      23
    ],
    "96995ef2": [
      51,
      53,
      79,
      80
    ],
    "279d461c": [
      51,
      53,
      79,
      80
    ],
    "9774a11e": [
      50,
      78
    ],
    "506705f1": [
      40,
      68,
      11,
      21
    ],
    "45f8418e": [
      30,
      58
    ],
    "6cb92845": [
      29,
      57,
      3,
      4,
      5,
      7,
      12,
      14,
      18,
      19,
      20,
      23
    ],
    "44cd40e7": [
      27,
      55
    ],
    "38284e6e": [
      50,
      78
    ],
    "5b037486": [
      50,
      78
    ],
    "510c102d": [
      27,
      55
    ],
    "01f2dbf9": [
      27,
      55
    ],
    "ebfdcbea": [
      50,
      78
    ],
    "75fb3764": [
      50,
      78
    ],
    "058123ac": [
      50,
      78
    ],
    "1d9d16f0": [
      37,
      65
    ],
    "d977cba8": [
      50,
      78
    ],
    "075226eb": [
      50,
      78
    ],
    "359fbbac": [
      28,
      56,
      3,
      5,
      8,
      10,
      12,
      15,
      16,
      22,
      24,
      25,
      26
    ],
    "277ae1bf": [
      50,
      78
    ],
    "d0761640": [
      50,
      78
    ],
    "0530483a": [
      50,
      78
    ],
    "33deceac": [
      27,
      55
    ],
    "649400e6": [
      35,
      63
    ],
    "33721c5e": [
      37,
      65
    ],
    "fa6efade": [
      50,
      78
    ],
    "c59c842a": [
      40,
      68,
      11,
      21
    ],
    "7dda5b8e": [
      44,
      72
    ],
    "540c40de": [
      50,
      78
    ],
    "2f3d234c": [
      40,
      68,
      11,
      21
    ],
    "3bf13600": [
      50,
      78
    ],
    "7cad647b": [
      29,
      57,
      3,
      4,
      5,
      7,
      12,
      14,
      18,
      19,
      20,
      23
    ],
    "4988fe68": [
      44,
      72
    ],
    "d009c7a2": [
      50,
      78
    ],
    "54ff955e": [
      40,
      68,
      11,
      21
    ],
    "3ddc0848": [
      31,
      59
    ],
    "fd8bc70e": [
      51,
      53,
      79,
      80
    ],
    "45d9f5a4": [
      27,
      55
    ],
    "3c552648": [
      31,
      59
    ],
    "10b059c5": [
      34,
      62
    ],
    "38b07cb4": [
      34,
      62
    ],
    "cd67a1b2": [
      37,
      65
    ],
    "471f6c5a": [
      36,
      64
    ],
    "ed979e8e": [
      50,
      78
    ],
    "146f3552": [
      27,
      55
    ],
    "2cc56ace": [
      28,
      56,
      3,
      5,
      8,
      10,
      12,
      15,
      16,
      22,
      24,
      25,
      26
    ],
    "0aef9c42": [
      50,
      78
    ],
    "cd271378": [
      50,
      78
    ],
    "5df5d7ff": [
      27,
      55
    ],
    "4bd20bd2": [
      50,
      78
    ],
    "4bbea852": [
      27,
      55
    ],
    "726b9090": [
      41,
      69
    ],
    "76f222fd": [
      48,
      76
    ],
    "614cf3be": [
      51,
      53,
      79,
      80
    ],
    "4cdc60d7": [
      51,
      53,
      79,
      80
    ],
    "eb0610e6": [
      27,
      55
    ],
    "65be0027": [
      42,
      70
    ],
    "4aa2dea8": [
      27,
      55
    ],
    "8cdaec5c": [
      50,
      78
    ],
    "1a2cfa92": [
      50,
      78
    ],
    "7e7ed71e": [
      27,
      55
    ],
    "f0302808": [
      31,
      59
    ],
    "9e204c38": [
      41,
      69
    ],
    "d0c93682": [
      51,
      53,
      79,
      80
    ],
    "60c5e423": [
      44,
      72
    ],
    "79806f84": [
      36,
      64
    ],
    "3115975a": [
      31,
      59
    ],
    "176872da": [
      27,
      55
    ],
    "7d75025c": [
      33,
      61
    ],
    "371afe04": [
      50,
      78
    ],
    "5d429514": [
      50,
      78
    ],
    "cf12233c": [
      50,
      78
    ],
    "78bdb89d": [
      27,
      55
    ],
    "a5ad0ec0": [
      50,
      78
    ],
    "293b2f3a": [
      43,
      71
    ],
    "49198f4f": [
      35,
      63
    ],
    "35c19a48": [
      27,
      55
    ],
    "1e826b80": [
      29,
      57,
      3,
      4,
      5,
      7,
      12,
      14,
      18,
      19,
      20,
      23
    ],
    "4bbe5bd7": [
      50,
      78
    ],
    "2aa8f33e": [
      50,
      78
    ],
    "3417f3b8": [
      51,
      53,
      79,
      80
    ],
    "332f29e6": [
      35,
      63
    ],
    "35476e67": [
      38,
      66
    ],
    "3a400a4f": [
      32,
      60
    ],
    "4dad4a5c": [
      50,
      78
    ],
    "06cc7700": [
      30,
      58
    ],
    "5e4cf584": [
      51,
      53,
      79,
      80
    ],
    "4b26b5a1": [
      33,
      61
    ],
    "46807bf1": [
      31,
      59
    ],
    "f944bf2c": [
      38,
      66
    ],
    "586b438e": [
      50,
      78
    ],
    "2167d242": [
      50,
      78
    ],
    "3618cbf5": [
      51,
      53,
      79,
      80
    ],
    "2a42249a": [
      27,
      55
    ],
    "52c2940f": [
      27,
      55
    ],
    "5fccbf3a": [
      50,
      78
    ],
    "576c327f": [
      50,
      78
    ],
    "4861c142": [
      50,
      78
    ],
    "776b0724": [
      40,
      68,
      11,
      21
    ],
    "5dbb6990": [
      40,
      68,
      11,
      21
    ],
    "32f8bf46": [
      50,
      78
    ],
    "c25ce508": [
      28,
      56,
      3,
      5,
      8,
      10,
      12,
      15,
      16,
      22,
      24,
      25,
      26
    ],
    "7590f2f4": [
      36,
      64
    ],
    "d68c48ea": [
      50,
      78
    ],
    "7b943bb1": [
      51,
      53,
      79,
      80
    ],
    "00534c16": [
      43,
      71
    ],
    "307ef1b5": [
      50,
      78
    ],
    "597e9fcb": [
      50,
      78
    ],
    "f07b8bf2": [
      50,
      78
    ],
    "3e4cdf82": [
      50,
      78
    ],
    "6fef2f14": [
      50,
      78
    ],
    "58c07dc0": [
      28,
      56,
      3,
      5,
      8,
      10,
      12,
      15,
      16,
      22,
      24,
      25,
      26
    ],
    "7cc4a1e7": [
      34,
      62
    ],
    "5b05dade": [
      44,
      72
    ],
    "0f4a66c0": [
      50,
      78
    ],
    "4336b49e": [
      33,
      61
    ],
    "06690b23": [
      27,
      55
    ],
    "23ac082c": [
      28,
      56,
      3,
      5,
      8,
      10,
      12,
      15,
      16,
      22,
      24,
      25,
      26
    ],
    "407bba38": [
      51,
      53,
      79,
      80
    ],
    "1e2df26a": [
      29,
      57,
      3,
      4,
      5,
      7,
      12,
      14,
      18,
      19,
      20,
      23
    ],
    "a91b00d2": [
      50,
      78
    ],
    "7d175bdf": [
      28,
      56,
      3,
      5,
      8,
      10,
      12,
      15,
      16,
      22,
      24,
      25,
      26
    ],
    "7629c062": [
      35,
      63
    ],
    "508b39f2": [
      33,
      61
    ],
    "57f45690": [
      50,
      78
    ],
    "4d88bff0": [
      51,
      53,
      79,
      80
    ],
    "f4e02920": [
      35,
      63
    ],
    "cf1a67f0": [
      50,
      78
    ],
    "6670b63d": [
      27,
      55
    ],
    "01a26c8a": [
      38,
      66
    ],
    "325ca316": [
      39,
      67,
      2,
      13
    ],
    "081fd51e": [
      51,
      53,
      79,
      80
    ],
    "002c6857": [
      51,
      53,
      79,
      80
    ],
    "8e99b716": [
      45,
      73
    ],
    "b446b85e": [
      51,
      53,
      79,
      80
    ],
    "01b9ccb4": [
      42,
      70
    ],
    "1fc99e40": [
      51,
      53,
      79,
      80
    ],
    "1aaef7e1": [
      50,
      78
    ],
    "21e740dd": [
      33,
      61
    ],
    "3bf6af2e": [
      38,
      66
    ],
    "444f0328": [
      28,
      56,
      3,
      5,
      8,
      10,
      12,
      15,
      16,
      22,
      24,
      25,
      26
    ],
    "2e9ec190": [
      34,
      62
    ],
    "179579ec": [
      37,
      65
    ],
    "660009e6": [
      50,
      78
    ],
    "0bbf6adc": [
      50,
      78
    ],
    "236bd1b9": [
      31,
      59
    ],
    "665d3b5a": [
      41,
      69
    ],
    "400add81": [
      27,
      55
    ],
    "1682c4ee": [
      38,
      66
    ],
    "7d0abf54": [
      39,
      67,
      2,
      13
    ],
    "096b56a2": [
      50,
      78
    ],
    "045607c6": [
      39,
      67,
      2,
      13
    ],
    "ab8bf98e": [
      27,
      55
    ],
    "cc80801c": [
      51,
      53,
      79,
      80
    ],
    "02ecf671": [
      50,
      78
    ],
    "91872ece": [
      33,
      61
    ],
    "4e8cbe28": [
      50,
      78
    ],
    "6a0d9e17": [
      50,
      78
    ],
    "2feec176": [
      44,
      72
    ],
    "56cf9822": [
      38,
      66
    ],
    "39dc4c9a": [
      36,
      64
    ],
    "0ee48b9b": [
      43,
      71
    ],
    "ca952142": [
      51,
      53,
      79,
      80
    ],
    "73936d8c": [
      51,
      53,
      79,
      80
    ],
    "882134d6": [
      51,
      53,
      79,
      80
    ],
    "6ab4b91c": [
      43,
      71
    ],
    "70edddab": [
      28,
      56,
      3,
      5,
      8,
      10,
      12,
      15,
      16,
      22,
      24,
      25,
      26
    ],
    "0d8c0014": [
      28,
      56,
      3,
      5,
      8,
      10,
      12,
      15,
      16,
      22,
      24,
      25,
      26
    ],
    "e47f151c": [
      51,
      53,
      79,
      80
    ],
    "6fcd9482": [
      36,
      64
    ],
    "41082fa8": [
      28,
      56,
      3,
      5,
      8,
      10,
      12,
      15,
      16,
      22,
      24,
      25,
      26
    ],
    "61ce23bf": [
      50,
      78
    ],
    "af6b272e": [
      31,
      59
    ],
    "04fea8df": [
      37,
      65
    ],
    "f22d94cc": [
      28,
      56,
      3,
      5,
      8,
      10,
      12,
      15,
      16,
      22,
      24,
      25,
      26
    ],
    "2e26a384": [
      27,
      55
    ],
    "2f4761f0": [
      29,
      57,
      3,
      4,
      5,
      7,
      12,
      14,
      18,
      19,
      20,
      23
    ],
    "23399b73": [
      51,
      53,
      79,
      80
    ],
    "0f73695c": [
      28,
      56,
      3,
      5,
      8,
      10,
      12,
      15,
      16,
      22,
      24,
      25,
      26
    ],
    "d09e042c": [
      28,
      56,
      3,
      5,
      8,
      10,
      12,
      15,
      16,
      22,
      24,
      25,
      26
    ],
    "51a7f6d6": [
      27,
      55
    ],
    "254a04c0": [
      32,
      60
    ],
    "64428ca8": [
      51,
      53,
      79,
      80
    ],
    "3a20bdc6": [
      27,
      55
    ],
    "2b667a1d": [
      28,
      56,
      3,
      5,
      8,
      10,
      12,
      15,
      16,
      22,
      24,
      25,
      26
    ],
    "c7140f82": [
      38,
      66
    ],
    "123c4d9c": [
      29,
      57,
      3,
      4,
      5,
      7,
      12,
      14,
      18,
      19,
      20,
      23
    ],
    "4eba1ff0": [
      50,
      78
    ],
    "5687e44a": [
      34,
      62
    ],
    "7dbf52d6": [
      51,
      53,
      79,
      80
    ],
    "330bc358": [
      51,
      53,
      79,
      80
    ],
    "2e842dcd": [
      35,
      63
    ],
    "3478229c": [
      50,
      78
    ],
    "01e545c0": [
      50,
      78
    ],
    "4b3ecf44": [
      51,
      53,
      79,
      80
    ],
    "3ed0cf81": [
      47,
      75,
      6,
      17
    ],
    "0e5ac9e7": [
      50,
      78
    ],
    "5fe9bf50": [
      28,
      56,
      3,
      5,
      8,
      10,
      12,
      15,
      16,
      22,
      24,
      25,
      26
    ],
    "01513238": [
      50,
      78
    ],
    "d8020760": [
      31,
      59
    ],
    "4ed2a7b8": [
      28,
      56,
      3,
      5,
      8,
      10,
      12,
      15,
      16,
      22,
      24,
      25,
      26
    ],
    "1f32db5e": [
      27,
      55
    ],
    "6b6fbb86": [
      51,
      53,
      79,
      80
    ],
    "cd1591b6": [
      51,
      53,
      79,
      80
    ],
    "c75eccbc": [
      51,
      53,
      79,
      80
    ],
    "06dced83": [
      51,
      53,
      79,
      80
    ],
    "54eee163": [
      36,
      64
    ],
    "399d42ac": [
      31,
      59
    ],
    "1a72acb2": [
      33,
      61
    ],
    "d1221baa": [
      28,
      56,
      3,
      5,
      8,
      10,
      12,
      15,
      16,
      22,
      24,
      25,
      26
    ],
    "7c9cf7b9": [
      29,
      57,
      3,
      4,
      5,
      7,
      12,
      14,
      18,
      19,
      20,
      23
    ],
    "721be068": [
      51,
      53,
      79,
      80
    ],
    "5e48dda1": [
      28,
      56,
      3,
      5,
      8,
      10,
      12,
      15,
      16,
      22,
      24,
      25,
      26
    ],
    "d5f72732": [
      28,
      56,
      3,
      5,
      8,
      10,
      12,
      15,
      16,
      22,
      24,
      25,
      26
    ],
    "7f1f69ca": [
      43,
      71
    ],
    "f61a2eaa": [
      28,
      56,
      3,
      5,
      8,
      10,
      12,
      15,
      16,
      22,
      24,
      25,
      26
    ],
    "53b7688c": [
      44,
      72
    ],
    "66c86c38": [
      50,
      78
    ],
    "668f63d6": [
      51,
      53,
      79,
      80
    ],
    "4ffc18a0": [
      37,
      65
    ],
    "6e2212ba": [
      36,
      64
    ],
    "77922f96": [
      27,
      55
    ],
    "2ecdbc40": [
      50,
      78
    ],
    "023f5f84": [
      50,
      78
    ],
    "21382f6e": [
      51,
      53,
      79,
      80
    ],
    "389fc305": [
      27,
      55
    ],
    "805890f8": [
      34,
      62
    ],
    "77d550da": [
      51,
      53,
      79,
      80
    ],
    "fd281b22": [
      50,
      78
    ],
    "65aa7a9d": [
      31,
      59
    ],
    "18c3829a": [
      50,
      78
    ],
    "0fc3bf2b": [
      38,
      66
    ],
    "444fb677": [
      51,
      53,
      79,
      80
    ],
    "61d807ea": [
      39,
      67,
      2,
      13
    ],
    "f3dea60e": [
      37,
      65
    ],
    "0a9bc8e8": [
      37,
      65
    ],
    "5763de9d": [
      50,
      78
    ],
    "7db36286": [
      44,
      72
    ],
    "e1648ee0": [
      27,
      55
    ],
    "1bad854c": [
      28,
      56,
      3,
      5,
      8,
      10,
      12,
      15,
      16,
      22,
      24,
      25,
      26
    ],
    "f29f1e58": [
      51,
      53,
      79,
      80
    ],
    "29b4c566": [
      32,
      60
    ],
    "717b1686": [
      50,
      78
    ],
    "02d8940c": [
      45,
      73
    ],
    "779c7919": [
      50,
      78
    ],
    "4806d61b": [
      27,
      55
    ],
    "7fbe81a3": [
      28,
      56,
      3,
      5,
      8,
      10,
      12,
      15,
      16,
      22,
      24,
      25,
      26
    ],
    "6999827d": [
      50,
      78
    ],
    "78e96042": [
      36,
      64
    ],
    "4f841e78": [
      42,
      70
    ],
    "1b2f6740": [
      50,
      78
    ],
    "4759a4a6": [
      50,
      78
    ],
    "33ecbd6c": [
      27,
      55
    ],
    "1d756418": [
      29,
      57,
      3,
      4,
      5,
      7,
      12,
      14,
      18,
      19,
      20,
      23
    ]
  }
}